[
  {
    "id": 1,
    "nombre": "pachamama",
    "imagenUrl": "https://picsum.photos/id/10/380/230",
    "votos": 0,
    "sincronizado": false
  },
  {
    "id": 2,
    "nombre": "maestro",
    "imagenUrl": "https://picsum.photos/id/456/380/230",
    "votos": 0,
    "sincronizado": false
  },
  {
    "id": 3,
    "nombre": "caramadunfga",
    "imagenUrl": "https://picsum.photos/id/652/380/230",
    "votos": 2,
    "sincronizado": false
  },
  {
    "id": 4,
    "nombre": "arequipa",
    "imagenUrl": "https://picsum.photos/id/147/380/230",
    "votos": 0,
    "sincronizado": false
  },
  {
    "id": 5,
    "nombre": "beluga",
    "imagenUrl": "https://picsum.photos/id/258/380/230",
    "votos": 0,
    "sincronizado": false
  },
  {
    "id": 6,
    "nombre": "periquto",
    "imagenUrl": "https://picsum.photos/id/954/380/230",
    "votos": 0,
    "sincronizado": false
  },
  {
    "id": 7,
    "nombre": "fido didoi",
    "imagenUrl": "https://picsum.photos/id/856/380/230",
    "votos": 0,
    "sincronizado": false
  },
  {
    "id": 8,
    "nombre": "test varios",
    "imagenUrl": "https://picsum.photos/id/174/380/230",
    "votos": 0,
    "sincronizado": false
  },
  {
    "id": 9,
    "nombre": "hmmmw",
    "imagenUrl": "https://picsum.photos/id/741/380/230",
    "votos": 0,
    "sincronizado": false
  },
  {
    "id": 10,
    "nombre": "felichita",
    "imagenUrl": "https://picsum.photos/id/852/380/230",
    "votos": 0,
    "sincronizado": false
  },
  {
    "id": 11,
    "nombre": "captr",
    "imagenUrl": "https://picsum.photos/id/856/380/230",
    "votos": 0,
    "sincronizado": false
  },
  {
    "id": 12,
    "nombre": "pedido",
    "imagenUrl": "https://picsum.photos/id/154/380/230",
    "votos": 2,
    "sincronizado": false
  },
  {
    "id": 13,
    "nombre": "calcular",
    "imagenUrl": "https://picsum.photos/id/154/380/230",
    "votos": 0,
    "sincronizado": false
  }
]